ncm163key.py
ncm_163key_parser-0.1.0.dist-info/LICENSE
ncm_163key_parser-0.1.0.dist-info/METADATA
ncm_163key_parser-0.1.0.dist-info/WHEEL
ncm_163key_parser-0.1.0.dist-info/top_level.txt
ncm_163key_parser-0.1.0.dist-info/RECORD
