Metadata-Version: 2.1
Name: ncm-163key-parser
Version: 0.1.0
Summary: 简单明了地解析和生成 163key 字符串
Author: nukemiko
License: Copyright 2023 nukemiko
Project-URL: Homepage, https://github.com/nukemiko/ncm-163key-parser
Project-URL: Bug Tracker, https://github.com/nukemiko/ncm-163key-parser/issues
Keywords: netease,163,163key,cloudmusic,ncm
Classifier: Programming Language :: Python :: 3
Classifier: Programming Language :: Python :: 3 :: Only
Classifier: License :: OSI Approved :: MIT License
Classifier: Operating System :: OS Independent
Requires-Python: >=3.9
License-File: LICENSE
Requires-Dist: attrs
Requires-Dist: pyaes
